balderhub/html/__init__.py
balderhub/html/_version.py
balderhub/html/lib/__init__.py
balderhub/html/lib/scenario_features/__init__.py
balderhub/html/lib/scenario_features/html_page.py
balderhub/html/lib/utils/__init__.py
balderhub/html/lib/utils/selector.py
balderhub/html/lib/utils/components/__init__.py
balderhub/html/lib/utils/components/abstract_html_input_element.py
balderhub/html/lib/utils/components/html_anchor_element.py
balderhub/html/lib/utils/components/html_body_element.py
balderhub/html/lib/utils/components/html_button_element.py
balderhub/html/lib/utils/components/html_div_element.py
balderhub/html/lib/utils/components/html_element.py
balderhub/html/lib/utils/components/html_form_element.py
balderhub/html/lib/utils/components/html_image_element.py
balderhub/html/lib/utils/components/html_label_element.py
balderhub/html/lib/utils/components/html_li_element.py
balderhub/html/lib/utils/components/html_ol_element.py
balderhub/html/lib/utils/components/html_option_element.py
balderhub/html/lib/utils/components/html_select_element.py
balderhub/html/lib/utils/components/html_span_element.py
balderhub/html/lib/utils/components/html_table_element.py
balderhub/html/lib/utils/components/html_tablecell_element.py
balderhub/html/lib/utils/components/html_tablerow_element.py
balderhub/html/lib/utils/components/html_textarea_element.py
balderhub/html/lib/utils/components/html_ul_element.py
balderhub/html/lib/utils/components/inputs/__init__.py
balderhub/html/lib/utils/components/inputs/html_button_input.py
balderhub/html/lib/utils/components/inputs/html_checkbox_input.py
balderhub/html/lib/utils/components/inputs/html_color_input.py
balderhub/html/lib/utils/components/inputs/html_date_input.py
balderhub/html/lib/utils/components/inputs/html_datetimelocal_input.py
balderhub/html/lib/utils/components/inputs/html_email_input.py
balderhub/html/lib/utils/components/inputs/html_file_input.py
balderhub/html/lib/utils/components/inputs/html_hidden_input.py
balderhub_html-0.0.1b1.dist-info/licenses/LICENSE
balderhub_html-0.0.1b1.dist-info/METADATA
balderhub_html-0.0.1b1.dist-info/WHEEL
balderhub_html-0.0.1b1.dist-info/top_level.txt
balderhub_html-0.0.1b1.dist-info/RECORD
